cliparoo/__about__.py
cliparoo/__init__.py
cliparoo/main.py
cliparoo-1.0.0.dist-info/METADATA
cliparoo-1.0.0.dist-info/WHEEL
cliparoo-1.0.0.dist-info/entry_points.txt
cliparoo-1.0.0.dist-info/licenses/LICENSE
cliparoo-1.0.0.dist-info/RECORD
