Metadata-Version: 2.4
Name: cliparoo
Version: 1.0.0
Summary: A video clipper, cutter, and splicer.
License-File: LICENSE
Requires-Python: >=3.13
Provides-Extra: dev
Requires-Dist: pytest>=8.4.1; extra == 'dev'
